[
  {
    "id": 25,
    "code": "PRE-20240814-00001"
  },
  {
    "id": 24,
    "code": "PRE-20240813-00001"
  },
  {
    "id": 23,
    "code": "PRE-20240812-00001"
  },
  {
    "id": 22,
    "code": "PRE-20240811-00001"
  },
  {
    "id": 21,
    "code": "PRE-20240810-00001"
  },
  {
    "id": 20,
    "code": "PRE-20240809-00001"
  },
  {
    "id": 19,
    "code": "PRE-20240808-00001"
  },
  {
    "id": 18,
    "code": "PRE-20240807-00001"
  },
  {
    "id": 17,
    "code": "PRE-20240806-00001"
  },
  {
    "id": 16,
    "code": "PRE-20240805-00001"
  },
  {
    "id": 15,
    "code": "PRE-20240804-00001"
  },
  {
    "id": 14,
    "code": "PRE-20240803-00001"
  },
  {
    "id": 13,
    "code": "PRE-20240802-00001"
  },
  {
    "id": 12,
    "code": "PRE-20240801-00001"
  },
  {
    "id": 11,
    "code": "PRE-20240730-00001"
  },
  {
    "id": 10,
    "code": "PRE-20240729-00001"
  },
  {
    "id": 9,
    "code": "PRE-20240728-00001"
  },
  {
    "id": 8,
    "code": "PRE-20240727-00001"
  },
  {
    "id": 7,
    "code": "PRE-20240726-00001"
  },
  {
    "id": 6,
    "code": "PRE-20240725-00001"
  },
  {
    "id": 5,
    "code": "PRE-20240724-00001"
  },
  {
    "id": 4,
    "code": "PRE-20240723-00001"
  },
  {
    "id": 3,
    "code": "PRE-20240722-00001"
  },
  {
    "id": 2,
    "code": "PRE-20240721-00001"
  },
  {
    "id": 1,
    "code": "PRE-20240720-00001"
  }
]
